LICENCE
MANIFEST.in
README.rst
readthedocs.txt
requirements.txt
setup.py
croppy/__init__.py
croppy/fields.py
croppy/models.py
croppy/views.py
django_croppy.egg-info/PKG-INFO
django_croppy.egg-info/SOURCES.txt
django_croppy.egg-info/dependency_links.txt
django_croppy.egg-info/requires.txt
django_croppy.egg-info/top_level.txt