Metadata-Version: 1.0
Name: django-croppy
Version: 0.1.0
Summary: Django model field to store custom image crops
Home-page: https://github.com/caffeinehit/django-croppy
Author: Alen Mujezinovic
Author-email: alen@caffeinehit.com
License: Copyright (c) 2012, Caffeinehit Ltd.
